zon/__init__.py
zon/error.py
zon/traits.py
zon-3.0.1.dist-info/licenses/LICENSE
zon-3.0.1.dist-info/METADATA
zon-3.0.1.dist-info/WHEEL
zon-3.0.1.dist-info/top_level.txt
zon-3.0.1.dist-info/RECORD
