Metadata-Version: 2.4
Name: zon
Version: 3.0.1
Summary: A Zod-like validation library for Python
Author-email: Nuno Pereira <nunoafonso2002@gmail.com>
Maintainer-email: Nuno Pereira <nunoafonso2002@gmail.com>
Project-URL: Homepage, https://github.com/Naapperas/zon
Project-URL: Issues, https://github.com/Naapperas/zon/issues
Classifier: Programming Language :: Python :: 3
Classifier: License :: OSI Approved :: MIT License
Classifier: Operating System :: OS Independent
Requires-Python: >=3.11
License-File: LICENSE
Requires-Dist: validators>0.28
Requires-Dist: typing_extensions>4.12
Provides-Extra: dev
Requires-Dist: black; extra == "dev"
Requires-Dist: build; extra == "dev"
Requires-Dist: pylint; extra == "dev"
Requires-Dist: pytest; extra == "dev"
Requires-Dist: pylint-pytest; extra == "dev"
Requires-Dist: pytest-cov; extra == "dev"
Dynamic: license-file
